ovos_tts_server/__init__.py
ovos_tts_server/__main__.py
ovos_tts_server/gradio_app.py
ovos_tts_server/version.py
ovos_tts_server/examples/rainbow.json
ovos_tts_server-0.1.3.dist-info/LICENSE.md
ovos_tts_server-0.1.3.dist-info/METADATA
ovos_tts_server-0.1.3.dist-info/WHEEL
ovos_tts_server-0.1.3.dist-info/entry_points.txt
ovos_tts_server-0.1.3.dist-info/top_level.txt
ovos_tts_server-0.1.3.dist-info/zip-safe
ovos_tts_server-0.1.3.dist-info/RECORD
