Metadata-Version: 2.1
Name: ovos-tts-server
Version: 0.1.3
Summary: simple FastAPI server to host TTS plugins as a service
Home-page: https://github.com/OpenVoiceOS/ovos-tts-server
Author: JarbasAi
Author-email: jarbasai@mailfence.com
License: Apache-2.0
Keywords: plugin TTS OVOS OpenVoiceOS
Classifier: Development Status :: 3 - Alpha
Classifier: Intended Audience :: Developers
Classifier: Topic :: Text Processing :: Linguistic
Classifier: License :: OSI Approved :: Apache Software License
Classifier: Programming Language :: Python :: 2
Classifier: Programming Language :: Python :: 2.7
Classifier: Programming Language :: Python :: 3
Classifier: Programming Language :: Python :: 3.0
Classifier: Programming Language :: Python :: 3.1
Classifier: Programming Language :: Python :: 3.2
Classifier: Programming Language :: Python :: 3.3
Classifier: Programming Language :: Python :: 3.4
Classifier: Programming Language :: Python :: 3.5
Classifier: Programming Language :: Python :: 3.6
License-File: LICENSE.md
Requires-Dist: ovos-plugin-manager<1.0.0,>=0.0.25
Requires-Dist: fastapi~=0.115
Requires-Dist: uvicorn~=0.34
Requires-Dist: gradio~=3.28
Requires-Dist: ovos-utils<1.0.0,>=0.0.38
